Workbook

Sheet 1
A1: Month
A2: {=_xlfn.TEXTAFTER(CELL("filename",A1),"]")} -> 1
B4: Planned | C4: Actual | D4: Left
A5: Incomes | B5: {=INDIRECT($A5&"_1[[#Totals];["&B$4&"]]")} -> 5700 | C5: {=INDIRECT($A5&"_1[[#Totals];["&C$4&"]]")} -> #REF! | D5: =B5-C5 -> #REF!
A6: Expenses | B6: {=INDIRECT($A6&"_1[[#Totals];["&B$4&"]]")} -> 3795 | C6: {=INDIRECT($A6&"_1[[#Totals];["&C$4&"]]")} -> #REF! | D6: =B6-C6 -> #REF!
A7: Savings | B7: {=INDIRECT($A7&"_1[[#Totals];["&B$4&"]]")} -> 0 | C7: {=INDIRECT($A7&"_1[[#Totals];["&C$4&"]]")} -> 0 | D7: =B7-C7 -> 0
A9: Balance | B9: =B5-B6-B7 -> 1905 | C9: =C5-C6-C7 -> #REF! | D9: =D7+D6-D5 -> #REF!
A11: Income | F11: Expenses | K11: Bills | Q11: Subscriptions | W11: Savings
A12: Source | B12: Planned | C12: Actual | D12: Left | F12: Category | G12: Planned | H12: Actual | I12: Left | K12: Source | L12: Due | M12: Planned | N12: Actual | O12: Left | Q12: Source | R12: Due | S12: Planned | T12: Actual | U12: Left | W12: Source | X12: Planned | Y12: Actual | Z12: Left
A13: Allowance | B13: 2500 | C13: {=_xlfn.XLOOKUP('1'!$A13,INDIRECT("'FinanseML.xlsx'!incomes_"&$A$2&"[Category]"),INDIRECT("'FinanseML.xlsx'!incomes_"&$A$2&"[Total]"),0,0,1)} -> #REF! | D13: ='1'!$B13-'1'!$C13 -> #REF! | F13: Accomodation | G13: 1735 | H13: {=-_xlfn.XLOOKUP('1'!$F13,INDIRECT("'FinanseML.xlsx'!expenses_"&$A$2&"[Category]"),INDIRECT("'FinanseML.xlsx'!expenses_"&$A$2&"[Total]"),0,0,1)} -> #REF! | I13: ='1'!$G13-'1'!$H13 -> #REF! | K13: Rent | L13: =DATE(2025,$A$2,10) -> 45667 | M13: 1500 | Q13: Spotify | R13: =DATE(2025,$A$2,RANDBETWEEN(1,28)) -> 45663 | S13: 12.99 | W13: Laptop | X13: 500 | Z13: =savings_1[[#This Row],[Planned]]-savings_1[[#This Row],[Actual]] -> 500
A14: Financial | B14: 300 | C14: {=_xlfn.XLOOKUP('1'!$A14,INDIRECT("'FinanseML.xlsx'!incomes_"&$A$2&"[Category]"),INDIRECT("'FinanseML.xlsx'!incomes_"&$A$2&"[Total]"),0,0,1)} -> #REF! | D14: ='1'!$B14-'1'!$C14 -> #REF! | F14: Clothing | G14: 200 | H14: {=-_xlfn.XLOOKUP('1'!$F14,INDIRECT("'FinanseML.xlsx'!expenses_"&$A$2&"[Category]"),INDIRECT("'FinanseML.xlsx'!expenses_"&$A$2&"[Total]"),0,0,1)} -> #REF! | I14: ='1'!$G14-'1'!$H14 -> #REF! | K14: Electricity | L14: =DATE(2025,$A$2,10) -> 45667 | M14: 80 | Q14: Netflix | R14: =DATE(2025,$A$2,RANDBETWEEN(1,28)) -> 45664 | S14: 33 | W14: Summer holidays | X14: 800 | Z14: =savings_1[[#This Row],[Planned]]-savings_1[[#This Row],[Actual]] -> 800
A15: Gift | B15: 500 | C15: {=_xlfn.XLOOKUP('1'!$A15,INDIRECT("'FinanseML.xlsx'!incomes_"&$A$2&"[Category]"),INDIRECT("'FinanseML.xlsx'!incomes_"&$A$2&"[Total]"),0,0,1)} -> #REF! | D15: ='1'!$B15-'1'!$C15 -> #REF! | F15: Entertainment | G15: 300 | H15: {=-_xlfn.XLOOKUP('1'!$F15,INDIRECT("'FinanseML.xlsx'!expenses_"&$A$2&"[Category]"),INDIRECT("'FinanseML.xlsx'!expenses_"&$A$2&"[Total]"),0,0,1)} -> #REF! | I15: ='1'!$G15-'1'!$H15 -> #REF! | K15: Water | L15: =DATE(2025,$A$2,10) -> 45667 | M15: 35 | Q15: Bookbeat | R15: =DATE(2025,$A$2,RANDBETWEEN(1,28)) -> 45667 | S15: 22.99 | W15: Rainy Day | X15: 605 | Z15: =savings_1[[#This Row],[Planned]]-savings_1[[#This Row],[Actual]] -> 605
A16: Other incoms | B16: 100 | C16: {=_xlfn.XLOOKUP('1'!$A16,INDIRECT("'FinanseML.xlsx'!incomes_"&$A$2&"[Category]"),INDIRECT("'FinanseML.xlsx'!incomes_"&$A$2&"[Total]"),0,0,1)} -> #REF! | D16: ='1'!$B16-'1'!$C16 -> #REF! | F16: Groceries | G16: 750 | H16: {=-_xlfn.XLOOKUP('1'!$F16,INDIRECT("'FinanseML.xlsx'!expenses_"&$A$2&"[Category]"),INDIRECT("'FinanseML.xlsx'!expenses_"&$A$2&"[Total]"),0,0,1)} -> #REF! | I16: ='1'!$G16-'1'!$H16 -> #REF! | K16: Gas | L16: =DATE(2025,$A$2,10) -> 45667 | M16: 25 | Q16: ChatGPT | R16: =DATE(2025,$A$2,RANDBETWEEN(1,28)) -> 45676 | S16: 100 | Z16: =savings_1[[#This Row],[Planned]]-savings_1[[#This Row],[Actual]] -> 0
A17: Salary | B17: 1500 | C17: {=_xlfn.XLOOKUP('1'!$A17,INDIRECT("'FinanseML.xlsx'!incomes_"&$A$2&"[Category]"),INDIRECT("'FinanseML.xlsx'!incomes_"&$A$2&"[Total]"),0,0,1)} -> #REF! | D17: ='1'!$B17-'1'!$C17 -> #REF! | F17: Health&Beauty | G17: 130 | H17: {=-_xlfn.XLOOKUP('1'!$F17,INDIRECT("'FinanseML.xlsx'!expenses_"&$A$2&"[Category]"),INDIRECT("'FinanseML.xlsx'!expenses_"&$A$2&"[Total]"),0,0,1)} -> #REF! | I17: ='1'!$G17-'1'!$H17 -> #REF! | K17: Waste | L17: =DATE(2025,$A$2,10) -> 45667 | M17: 35 | Q17: Duolingo | R17: =DATE(2025,$A$2,RANDBETWEEN(1,28)) -> 45665 | S17: 42.69 | Z17: =savings_1[[#This Row],[Planned]]-savings_1[[#This Row],[Actual]] -> 0
A18: Scholarship | B18: 800 | C18: {=_xlfn.XLOOKUP('1'!$A18,INDIRECT("'FinanseML.xlsx'!incomes_"&$A$2&"[Category]"),INDIRECT("'FinanseML.xlsx'!incomes_"&$A$2&"[Total]"),0,0,1)} -> #REF! | D18: ='1'!$B18-'1'!$C18 -> #REF! | F18: Multimedia | G18: 130 | H18: {=-_xlfn.XLOOKUP('1'!$F18,INDIRECT("'FinanseML.xlsx'!expenses_"&$A$2&"[Category]"),INDIRECT("'FinanseML.xlsx'!expenses_"&$A$2&"[Total]"),0,0,1)} -> #REF! | I18: ='1'!$G18-'1'!$H18 -> #REF! | K18: Internet | L18: =DATE(2025,$A$2,10) -> 45667 | M18: 60 | Z18: =savings_1[[#This Row],[Planned]]-savings_1[[#This Row],[Actual]] -> 0
C19: {=_xlfn.XLOOKUP('1'!$A19,INDIRECT("'FinanseML.xlsx'!incomes_"&$A$2&"[Category]"),INDIRECT("'FinanseML.xlsx'!incomes_"&$A$2&"[Total]"),0,0,1)} -> #REF! | D19: ='1'!$B19-'1'!$C19 -> #REF! | F19: Other expences | G19: 200 | H19: {=-_xlfn.XLOOKUP('1'!$F19,INDIRECT("'FinanseML.xlsx'!expenses_"&$A$2&"[Category]"),INDIRECT("'FinanseML.xlsx'!expenses_"&$A$2&"[Total]"),0,0,1)} -> #REF! | I19: ='1'!$G19-'1'!$H19 -> #REF! | Z19: =savings_1[[#This Row],[Planned]]-savings_1[[#This Row],[Actual]] -> 0
C20: {=_xlfn.XLOOKUP('1'!$A20,INDIRECT("'FinanseML.xlsx'!incomes_"&$A$2&"[Category]"),INDIRECT("'FinanseML.xlsx'!incomes_"&$A$2&"[Total]"),0,0,1)} -> #REF! | D20: ='1'!$B20-'1'!$C20 -> #REF! | F20: Studies | G20: 200 | H20: {=-_xlfn.XLOOKUP('1'!$F20,INDIRECT("'FinanseML.xlsx'!expenses_"&$A$2&"[Category]"),INDIRECT("'FinanseML.xlsx'!expenses_"&$A$2&"[Total]"),0,0,1)} -> #REF! | I20: ='1'!$G20-'1'!$H20 -> #REF! | Z20: =savings_1[[#This Row],[Planned]]-savings_1[[#This Row],[Actual]] -> 0
C21: {=_xlfn.XLOOKUP('1'!$A21,INDIRECT("'FinanseML.xlsx'!incomes_"&$A$2&"[Category]"),INDIRECT("'FinanseML.xlsx'!incomes_"&$A$2&"[Total]"),0,0,1)} -> #REF! | D21: ='1'!$B21-'1'!$C21 -> #REF! | F21: Transportation | G21: 150 | H21: {=-_xlfn.XLOOKUP('1'!$F21,INDIRECT("'FinanseML.xlsx'!expenses_"&$A$2&"[Category]"),INDIRECT("'FinanseML.xlsx'!expenses_"&$A$2&"[Total]"),0,0,1)} -> #REF! | I21: ='1'!$G21-'1'!$H21 -> #REF! | Z21: =savings_1[[#This Row],[Planned]]-savings_1[[#This Row],[Actual]] -> 0
C22: {=_xlfn.XLOOKUP('1'!$A22,INDIRECT("'FinanseML.xlsx'!incomes_"&$A$2&"[Category]"),INDIRECT("'FinanseML.xlsx'!incomes_"&$A$2&"[Total]"),0,0,1)} -> #REF! | D22: ='1'!$B22-'1'!$C22 -> #REF! | I22: ='1'!$G22-'1'!$H22 -> 0 | Z22: =savings_1[[#This Row],[Planned]]-savings_1[[#This Row],[Actual]] -> 0
C23: {=_xlfn.XLOOKUP('1'!$A23,INDIRECT("'FinanseML.xlsx'!incomes_"&$A$2&"[Category]"),INDIRECT("'FinanseML.xlsx'!incomes_"&$A$2&"[Total]"),0,0,1)} -> #REF! | D23: ='1'!$B23-'1'!$C23 -> #REF! | I23: ='1'!$G23-'1'!$H23 -> 0 | Z23: =savings_1[[#This Row],[Planned]]-savings_1[[#This Row],[Actual]] -> 0
C24: {=_xlfn.XLOOKUP('1'!$A24,INDIRECT("'FinanseML.xlsx'!incomes_"&$A$2&"[Category]"),INDIRECT("'FinanseML.xlsx'!incomes_"&$A$2&"[Total]"),0,0,1)} -> #REF! | D24: ='1'!$B24-'1'!$C24 -> #REF! | I24: ='1'!$G24-'1'!$H24 -> 0 | Z24: =savings_1[[#This Row],[Planned]]-savings_1[[#This Row],[Actual]] -> 0
A25: Total | B25: =SUBTOTAL(109,incomes_1[Planned]) -> 5700 | C25: =SUBTOTAL(109,incomes_1[Actual]) -> #REF! | D25: =SUBTOTAL(109,incomes_1[Left]) -> #REF! | F25: Total | G25: =SUBTOTAL(109,expenses_1[Planned]) -> 3795 | H25: =SUBTOTAL(109,expenses_1[Actual]) -> #REF! | I25: =SUBTOTAL(109,expenses_1[Left]) -> #REF! | K25: Total | M25: =SUBTOTAL(109,bills_1[Planned]) -> 1735 | N25: =SUBTOTAL(109,bills_1[Actual]) -> 0 | O25: =SUBTOTAL(109,bills_1[Left]) -> 0 | Q25: Total | U25: =SUBTOTAL(103,subscriptions_1[Left]) -> 0 | W25: Total | Z25: =SUBTOTAL(103,savings_1[Left]) -> 12
A26: Total | B26: =SUBTOTAL(109,'1'!$B$13:$B$24) -> 5700 | C26: =SUBTOTAL(109,'1'!$C$13:$C$24) -> #REF! | D26: =SUBTOTAL(109,'1'!$D$13:$D$24) -> #REF! | F26: Total | G26: =SUBTOTAL(109,'1'!$G$13:$G$24) -> 3795 | H26: =SUBTOTAL(109,'1'!$H$13:$H$24) -> #REF! | I26: =SUBTOTAL(109,'1'!$I$13:$I$24) -> #REF! | K26: Total | M26: =SUBTOTAL(109,'1'!$M$13:$M$24) -> 1735 | N26: =SUBTOTAL(109,'1'!$N$13:$N$24) -> 0 | O26: =SUBTOTAL(109,'1'!$O$13:$O$24) -> 0 | Q26: Total | S26: =SUBTOTAL(109,'1'!$S$13:$S$24) -> 211.67 | T26: =SUBTOTAL(109,'1'!$T$13:$T$24) -> 0 | U26: =SUBTOTAL(109,'1'!$U$13:$U$24) -> 0 | W26: Total | X26: =SUBTOTAL(109,'1'!$X$13:$X$24) -> 1905 | Y26: =SUBTOTAL(109,'1'!$Y$13:$Y$24) -> 0 | Z26: =SUBTOTAL(109,'1'!$Z$13:$Z$24) -> 1905
